wikisets/__init__.py
wikisets/card_generator.py
wikisets/config.py
wikisets/pretrain.py
wikisets/sampler.py
wikisets/utils.py
wikisets/wikiset.py
wikisets-0.1.3.dist-info/METADATA
wikisets-0.1.3.dist-info/WHEEL
wikisets-0.1.3.dist-info/licenses/LICENSE
wikisets-0.1.3.dist-info/RECORD
