Metadata-Version: 2.4
Name: wikisets
Version: 0.1.3
Summary: Flexible Wikipedia dataset builder with sampling and pretraining support
Project-URL: Homepage, https://github.com/omarkamali/wikisets
Project-URL: Documentation, https://github.com/omarkamali/wikisets/tree/main/docs
Project-URL: Repository, https://github.com/omarkamali/wikisets
Project-URL: Issues, https://github.com/omarkamali/wikisets/issues
Author-email: Omar Kamali <wikisets@omarkama.li>
License: MIT
License-File: LICENSE
Keywords: dataset,machine-learning,nlp,pretraining,wikipedia
Classifier: Development Status :: 4 - Beta
Classifier: Intended Audience :: Developers
Classifier: Intended Audience :: Science/Research
Classifier: License :: OSI Approved :: MIT License
Classifier: Programming Language :: Python :: 3
Classifier: Programming Language :: Python :: 3.9
Classifier: Programming Language :: Python :: 3.10
Classifier: Programming Language :: Python :: 3.11
Classifier: Programming Language :: Python :: 3.12
Classifier: Programming Language :: Python :: 3.13
Classifier: Programming Language :: Python :: 3.14
Classifier: Topic :: Scientific/Engineering :: Artificial Intelligence
Requires-Python: >=3.9
Requires-Dist: datasets>=2.14.0
Requires-Dist: numpy>=1.20.0
Requires-Dist: tokenizers>=0.13.0
Requires-Dist: tqdm>=4.65.0
Requires-Dist: transformers>=4.30.0
Provides-Extra: dev
Requires-Dist: mypy>=1.0.0; extra == 'dev'
Requires-Dist: pytest-cov>=4.0.0; extra == 'dev'
Requires-Dist: pytest>=7.0.0; extra == 'dev'
Requires-Dist: ruff>=0.1.0; extra == 'dev'
